debugaid/__init__.py
debugaid-1.0.0.dist-info/licenses/LICENSE
debugaid-1.0.0.dist-info/METADATA
debugaid-1.0.0.dist-info/WHEEL
debugaid-1.0.0.dist-info/top_level.txt
debugaid-1.0.0.dist-info/RECORD
