Metadata-Version: 2.4
Name: debugaid
Version: 1.0.0
Summary: A lightweight Python toolkit for debugging and performance analysis
Author: FelineFantasy
Author-email: mailsalavata5@gmail.com
Classifier: Programming Language :: Python :: 3
Classifier: License :: OSI Approved :: MIT License
Classifier: Operating System :: OS Independent
Requires-Python: >=3.6
License-File: LICENSE
Dynamic: author
Dynamic: author-email
Dynamic: classifier
Dynamic: description
Dynamic: description-content-type
Dynamic: license-file
Dynamic: requires-python
Dynamic: summary
